SideScanSonarEditor/__init__.py
SideScanSonarEditor/app.py
SideScanSonarEditor/processing/xtf_to_image.py
SideScanSonarEditor/widgets/canvas.py
SideScanSonarEditor/widgets/draw_shapes.py
sidescansonareditor-1.0.0.dist-info/licenses/LICENSE
sidescansonareditor-1.0.0.dist-info/METADATA
sidescansonareditor-1.0.0.dist-info/WHEEL
sidescansonareditor-1.0.0.dist-info/entry_points.txt
sidescansonareditor-1.0.0.dist-info/top_level.txt
sidescansonareditor-1.0.0.dist-info/RECORD
