Metadata-Version: 2.4
Name: SideScanSonarEditor
Version: 1.0.0
Summary: A Python package for editing side-scan sonar data.
Author-email: Michal Motylinski <motylm66@gmail.com>
License: LICENSE
Project-URL: Repository, https://github.com/MichalMotylinski/SideScanSonarEditor
Requires-Python: >=3.9
License-File: LICENSE
Requires-Dist: numpy
Requires-Dist: opencv-python
Requires-Dist: pillow
Requires-Dist: pyproj
Requires-Dist: PyQt6
Requires-Dist: PyQt6-Qt6
Requires-Dist: PyQt6_sip
Requires-Dist: pyxtf
Requires-Dist: scipy
Provides-Extra: test
Requires-Dist: pytest; extra == "test"
Requires-Dist: pytest-qt; extra == "test"
Requires-Dist: mock; extra == "test"
Requires-Dist: certifi; extra == "test"
Dynamic: license-file
